<?xml version="1.0" encoding="utf-8"?>
 <extension version="3.0" type="template">
         <name>mc-de-burger</name>
         <creationDate>2014-10-07</creationDate>
         <author>VanArman</author>
         <authorEmail>dimaarman@gmail.com</authorEmail>
         <copyright>VanArman 2014</copyright>
         <license>GNU/GPL 2 or Later</license>
         <version>1.1.0</version>
         <files>
 		 <folder>css</folder>
                 <folder>js</folder>
                 <folder>html</folder>
                 <folder>images</folder>
                 <filename>index.php</filename>
                 <filename>templateDetails.xml</filename>
                 <filename>template_preview.png</filename>
                 <filename>template_thumbnail.png</filename>
         </files>
         <positions>
                 <position>mainmenu</position>
                 <position>search</position>
                 <position>additionalmenu</position>
                 <position>breadcrumbs</position>
                 <position>bigcentralslider</position>
                 <position>footer</position>
                 <position>small-map</position>
         </positions>
 </extension>